rn3/__init__.py
rn3/scrap_notes.text
rn3/startup_script.py
rn3/dataset/__init__.py
rn3/dataset/dataset_model.py
rn3/dataset/dataset_referencedata.py
rn3/dataset/dataset_schema.json
rn3/dataset/item.py
rn3/dataset/table.py
rn3/io/__init__.py
rn3/io/xlsx.py
rn3-0.0.15.dist-info/METADATA
rn3-0.0.15.dist-info/WHEEL
rn3-0.0.15.dist-info/licenses/LICENSE
rn3-0.0.15.dist-info/RECORD
